run_mdao/__init__.py
run_mdao/__main__.py
run_mdao/array_hashable.py
run_mdao/celery_tasks.py
run_mdao/csv_recorder.py
run_mdao/drivers.py
run_mdao/enum_mapper.py
run_mdao/parallel_execution.py
run_mdao/restart_recorder.py
run_mdao/testbenchcomponent.py
run_mdao/python_component/__init__.py
run_mdao/python_component/get_params_and_unknowns/__init__.py
run_mdao/python_component/get_params_and_unknowns/__main__.py
run_mdao-0.5.0.dist-info/METADATA
run_mdao-0.5.0.dist-info/WHEEL
run_mdao-0.5.0.dist-info/entry_points.txt
run_mdao-0.5.0.dist-info/top_level.txt
run_mdao-0.5.0.dist-info/RECORD
