Metadata-Version: 2.1
Name: run-mdao
Version: 0.5.0
Summary: Runs a mdao_config.json with OpenMDAO
Home-page: UNKNOWN
Author: MetaMorph Software, Inc
Author-email: ksmyth@metamorphsoftware.com
License: UNKNOWN
Project-URL: Source, https://github.com/metamorph-inc/run_mdao
Platform: UNKNOWN
Requires-Dist: mms-openmdao (<2,>=1.7.5rc1)
Requires-Dist: testbenchexecutor
